opentelemetry/instrumentation/wsgi/__init__.py
opentelemetry/instrumentation/wsgi/package.py
opentelemetry/instrumentation/wsgi/version.py
opentelemetry_instrumentation_wsgi-0.40b0.dist-info/METADATA
opentelemetry_instrumentation_wsgi-0.40b0.dist-info/WHEEL
opentelemetry_instrumentation_wsgi-0.40b0.dist-info/licenses/LICENSE
opentelemetry_instrumentation_wsgi-0.40b0.dist-info/RECORD
